odoo/addons/stock_picking_copy_qty/__init__.py
odoo/addons/stock_picking_copy_qty/__manifest__.py
odoo/addons/stock_picking_copy_qty/models/__init__.py
odoo/addons/stock_picking_copy_qty/models/stock.py
odoo/addons/stock_picking_copy_qty/views/stock.xml
odoo12_addon_stock_picking_copy_qty-12.0.1.0.0.99.dev1.dist-info/METADATA
odoo12_addon_stock_picking_copy_qty-12.0.1.0.0.99.dev1.dist-info/WHEEL
odoo12_addon_stock_picking_copy_qty-12.0.1.0.0.99.dev1.dist-info/top_level.txt
odoo12_addon_stock_picking_copy_qty-12.0.1.0.0.99.dev1.dist-info/RECORD
